{
  "sections": {
    "featured_products": {
      "type": "featured-collection",
      "settings": {
        "title": "Featured products",
        "collection": "all",
        "products_to_show": 4,
        "show_view_all": true,
        "swipe_on_mobile": false,
        "image_ratio": "square",
        "show_secondary_image": false,
        "add_image_padding": false,
        "show_image_outline": true,
        "show_vendor": false,
        "show_rating": false
      }
    },
    "1636383480a171f0da": {
      "type": "featured-product",
      "blocks": {
        "1636383480a171f0da-0": {
          "type": "text",
          "settings": {
            "text": "",
            "text_style": "uppercase"
          }
        },
        "1636383480a171f0da-1": {
          "type": "title",
          "settings": {
          }
        },
        "1636383480a171f0da-2": {
          "type": "text",
          "settings": {
            "text": "",
            "text_style": "subtitle"
          }
        },
        "1636383480a171f0da-3": {
          "type": "price",
          "settings": {
          }
        },
        "1636383480a171f0da-4": {
          "type": "variant_picker",
          "settings": {
            "picker_type": "button"
          }
        },
        "1636383480a171f0da-5": {
          "type": "quantity_selector",
          "settings": {
          }
        },
        "1636383480a171f0da-6": {
          "type": "buy_buttons",
          "settings": {
            "show_dynamic_checkout": true
          }
        },
        "1636383480a171f0da-7": {
          "type": "share",
          "settings": {
            "share_label": "Share"
          }
        }
      },
      "block_order": [
        "1636383480a171f0da-0",
        "1636383480a171f0da-1",
        "1636383480a171f0da-2",
        "1636383480a171f0da-3",
        "1636383480a171f0da-4",
        "1636383480a171f0da-5",
        "1636383480a171f0da-6",
        "1636383480a171f0da-7"
      ],
      "settings": {
        "product": "classic-varsity-top",
        "secondary_background": false,
        "hide_variants": false,
        "enable_video_looping": false
      }
    },
    "1636824819d559f0a3": {
      "type": "featured-collection",
      "settings": {
        "title": "Featured collection",
        "collection": "",
        "products_to_show": 4,
        "show_view_all": true,
        "swipe_on_mobile": false,
        "image_ratio": "adapt",
        "show_secondary_image": false,
        "add_image_padding": false,
        "show_image_outline": true,
        "show_vendor": false,
        "show_rating": false
      }
    }
  },
  "order": [
    "featured_products",
    "1636383480a171f0da",
    "1636824819d559f0a3"
  ]
}
